__init__.py
common/__init__.py
common/decorator.py
common/logger.py
common/type_def.py
common/utils.py
core/__init__.py
core/executor.py
core/loaders.py
core/models/__init__.py
core/models/exceptions.py
core/models/phases.py
core/models/pipeline.py
core/orchestrator.py
core/parsers/__init__.py
core/parsers/pipeline_parser.py
core/parsers/plugin_parser.py
core/parsers/yaml_parser.py
core/plugins.py
entrypoint.py
plugins/__init__.py
plugins/extract/__init__.py
plugins/load/__init__.py
plugins/merge/__init__.py
plugins/transform/__init__.py
plugins/transform/native.py
plugins/transform/pyspark.py
pipeline_orchestrator-0.0.0a1.dist-info/LICENSE
pipeline_orchestrator-0.0.0a1.dist-info/METADATA
pipeline_orchestrator-0.0.0a1.dist-info/WHEEL
pipeline_orchestrator-0.0.0a1.dist-info/RECORD
